anntonia/.gitignore
anntonia/README.md
anntonia/__init__.py
anntonia/anntonia-env.txt
anntonia/communication.py
anntonia/globals.py
anntonia/server/actions.py
anntonia/server/internal_structures.py
anntonia/server/server.py
anntonia/server/state.py
anntonia/utils/dimensionality_reduction.py
anntonia/utils/plot.py
anntonia/utils/relevance_propagation.py
anntonia/visualizers/components.py
anntonia/visualizers/data_transformation.py
anntonia/visualizers/linear_model/edges.py
anntonia/visualizers/linear_model/linear_model_visualizer.py
anntonia/visualizers/linear_model/node_coordinates.py
anntonia/visualizers/linear_model/node_values.py
anntonia-0.1.0.dist-info/METADATA
anntonia-0.1.0.dist-info/WHEEL
anntonia-0.1.0.dist-info/licenses/LICENSE
anntonia-0.1.0.dist-info/RECORD
