Metadata-Version: 2.1
Name: anntonia
Version: 0.1.0
Summary: Artificial Neural Network to Node-link Immersive Analytics
Project-URL: Homepage, https://vr.rwth-aachen.de
Author-email: Martin Bellgardt <bellgardt@vr.rwth-aachen.de>
License: MIT License
License-File: LICENSE
Classifier: License :: OSI Approved :: MIT License
Classifier: Operating System :: Microsoft :: Windows
Classifier: Programming Language :: Python :: 3
Requires-Python: >=3.7
Requires-Dist: bson
Requires-Dist: matplotlib
Requires-Dist: numpy
Requires-Dist: pillow
Requires-Dist: scikit-learn
Requires-Dist: scipy
Requires-Dist: websockets
